pingsubnet/IPv4.py
pingsubnet/__init__.py
pingsubnet/main.py
pingsubnet-0.1.1.dist-info/licenses/LICENSE
pingsubnet-0.1.1.dist-info/METADATA
pingsubnet-0.1.1.dist-info/WHEEL
pingsubnet-0.1.1.dist-info/entry_points.txt
pingsubnet-0.1.1.dist-info/top_level.txt
pingsubnet-0.1.1.dist-info/RECORD
