Metadata-Version: 2.4
Name: pingsubnet
Version: 0.1.1
Summary: A Python script that pings all potential IPv4 addresses in a subnet and reports response times.
Author-email: Adam Howell <698228+AdamJHowell@users.noreply.github.com>
License-Expression: MIT
Classifier: Development Status :: 3 - Alpha
Classifier: Programming Language :: Python :: 3
Classifier: Programming Language :: Python :: 3.9
Classifier: Programming Language :: Python :: 3.10
Classifier: Programming Language :: Python :: 3.11
Classifier: Programming Language :: Python :: 3.12
Classifier: Programming Language :: Python :: 3.13
Classifier: Programming Language :: Python :: 3.14
Classifier: Operating System :: OS Independent
Classifier: Topic :: System :: Networking
Requires-Python: >=3.9
License-File: LICENSE
Requires-Dist: psutil
Requires-Dist: ping3
Dynamic: license-file
